simplecalcamir/__init__.py
simplecalcamir-0.0.3.dist-info/LICENCE.txt
simplecalcamir-0.0.3.dist-info/METADATA
simplecalcamir-0.0.3.dist-info/WHEEL
simplecalcamir-0.0.3.dist-info/top_level.txt
simplecalcamir-0.0.3.dist-info/RECORD
